setup.cfg
setup.py
digani/__init__.py
digani/data_loader.py
digani/extractor.py
digani/identifier.py
digani/rule_generator.py
digani.egg-info/PKG-INFO
digani.egg-info/SOURCES.txt
digani.egg-info/dependency_links.txt
digani.egg-info/requires.txt
digani.egg-info/top_level.txt
digani/attr_func/__init__.py
digani/attr_func/age.py
digani/attr_func/base.py
digani/attr_func/breast.py
digani/attr_func/city.py
digani/attr_func/date.py
digani/attr_func/email.py
digani/attr_func/ethnicity.py
digani/attr_func/eye.py
digani/attr_func/hair.py
digani/attr_func/identifier.py
digani/attr_func/junk.py
digani/attr_func/location.py
digani/attr_func/nationality.py
digani/attr_func/person.py
digani/attr_func/price.py
digani/attr_func/state.py
digani/attr_func/telephone.py
digani/attr_func/text.py
digani/attr_func/website.py
digani/attr_func/zipcode.py
digani/common/__init__.py
digani/common/gram_helper.py
digani/common/string_helper.py
digani/common/trie_helper.py
digani/common/token_helper/__init__.py
digani/common/token_helper/crf_tokenizer.py
digani/res/__init__.py
digani/res/base.py
digani/res/breast/__init__.py
digani/res/breast/breast_size.json
digani/res/breast/breast_unit.json
digani/res/city/__init__.py
digani/res/city/big_names.json
digani/res/city/extra_places.json
digani/res/city/names.json
digani/res/city/names_small.json
digani/res/common/__init__.py
digani/res/common/color.json
digani/res/country/__init__.py
digani/res/country/country_abbreviation.json
digani/res/country/country_names.json
digani/res/country/names.json
digani/res/email/__init__.py
digani/res/email/email_extractor.py
digani/res/ethnicity/__init__.py
digani/res/ethnicity/names.json
digani/res/eye/__init__.py
digani/res/hair/__init__.py
digani/res/nationality/__init__.py
digani/res/nationality/names.json
digani/res/person/__init__.py
digani/res/person/names.json
digani/res/state/__init__.py
digani/res/state/names.json
digani/res/state/state_abbreviation.json
digani/res/zipcode/__init__.py
digani/res/zipcode/names.json