Metadata-Version: 1.1
Name: digani
Version: 0.1.2
Summary: automatically identify column names
Home-page: https://github.com/ZwEin27/dig-attribute-name-identification
Author: Lingzhe Teng
Author-email: zwein27@gmail.com
License: UNKNOWN
Download-URL: https://github.com/ZwEin27/dig-attribute-name-identification/tarball/0.1.2
Keywords: dig,name,identify,attribute,column
Platform: UNKNOWN
